{
  "4240": {
    "from": 28040,
    "to": 4240,
    "cost": {
      "coins": 500,
      "items": [
        {
          "id": 18105,
          "amount": 24
        },
        {
          "id": 18108,
          "amount": 18
        },
        {
          "id": 18115,
          "amount": 9
        }
      ]
    }
  },
  "4260": {
    "from": 4240,
    "to": 4260,
    "cost": {
      "coins": 4000,
      "items": [
        {
          "id": 18123,
          "amount": 9
        },
        {
          "id": 18106,
          "amount": 30
        },
        {
          "id": 18116,
          "amount": 30
        }
      ]
    }
  },
  "4340": {
    "from": 18140,
    "to": 4340,
    "cost": {
      "coins": 500,
      "items": [
        {
          "id": 18105,
          "amount": 24
        },
        {
          "id": 18108,
          "amount": 18
        },
        {
          "id": 18115,
          "amount": 9
        }
      ]
    }
  },
  "5440": {
    "from": 5340,
    "to": 5440,
    "cost": {
      "coins": 450,
      "items": [
        {
          "id": 18108,
          "amount": 18
        },
        {
          "id": 18105,
          "amount": 12
        },
        {
          "id": 18113,
          "amount": 9
        }
      ]
    }
  },
  "5600": {
    "from": 5440,
    "to": 5600,
    "cost": {
      "coins": 400,
      "items": [
        {
          "id": 18108,
          "amount": 5
        },
        {
          "id": 18105,
          "amount": 4
        },
        {
          "id": 18113,
          "amount": 3
        }
      ]
    }
  },
  "5640": {
    "from": 5620,
    "to": 5640,
    "cost": {
      "coins": 1500,
      "items": [
        {
          "id": 18119,
          "amount": 3
        },
        {
          "id": 18109,
          "amount": 15
        },
        {
          "id": 18114,
          "amount": 12
        }
      ]
    }
  },
  "7300": {
    "from": 90900,
    "to": 7300,
    "cost": {
      "coins": 2500,
      "items": [
        {
          "id": 18126,
          "amount": 6
        },
        {
          "id": 18117,
          "amount": 6
        },
        {
          "id": 18103,
          "amount": 24
        }
      ]
    }
  },
  "11060": {
    "from": 11040,
    "to": 11060,
    "cost": {
      "coins": 50,
      "items": [
        {
          "id": 18101,
          "amount": 12
        },
        {
          "id": 18110,
          "amount": 9
        },
        {
          "id": 18107,
          "amount": 9
        }
      ]
    }
  },
  "11140": {
    "from": 11060,
    "to": 11140,
    "cost": {
      "coins": 400,
      "items": [
        {
          "id": 18102,
          "amount": 18
        },
        {
          "id": 18111,
          "amount": 15
        },
        {
          "id": 18108,
          "amount": 15
        }
      ]
    }
  },
  "11160": {
    "from": 11140,
    "to": 11160,
    "cost": {
      "coins": 500,
      "items": [
        {
          "id": 18102,
          "amount": 24
        },
        {
          "id": 18111,
          "amount": 18
        },
        {
          "id": 18108,
          "amount": 18
        }
      ]
    }
  },
  "11240": {
    "from": 11160,
    "to": 11240,
    "cost": {
      "coins": 1500,
      "items": [
        {
          "id": 18117,
          "amount": 3
        },
        {
          "id": 18112,
          "amount": 15
        },
        {
          "id": 18109,
          "amount": 15
        }
      ]
    }
  },
  "11260": {
    "from": 11240,
    "to": 11260,
    "cost": {
      "coins": 2500,
      "items": [
        {
          "id": 18126,
          "amount": 6
        },
        {
          "id": 18117,
          "amount": 6
        },
        {
          "id": 18103,
          "amount": 24
        }
      ]
    }
  },
  "12060": {
    "from": 12040,
    "to": 12060,
    "cost": {
      "coins": 50,
      "items": [
        {
          "id": 18101,
          "amount": 12
        },
        {
          "id": 18110,
          "amount": 9
        },
        {
          "id": 18107,
          "amount": 9
        }
      ]
    }
  },
  "12140": {
    "from": 12060,
    "to": 12140,
    "cost": {
      "coins": 400,
      "items": [
        {
          "id": 18102,
          "amount": 18
        },
        {
          "id": 18111,
          "amount": 15
        },
        {
          "id": 18108,
          "amount": 15
        }
      ]
    }
  },
  "12160": {
    "from": 12140,
    "to": 12160,
    "cost": {
      "coins": 2000,
      "items": [
        {
          "id": 18117,
          "amount": 3
        },
        {
          "id": 18103,
          "amount": 21
        },
        {
          "id": 18109,
          "amount": 21
        }
      ]
    }
  },
  "12200": {
    "from": 12160,
    "to": 12200,
    "cost": {
      "coins": 2500,
      "items": [
        {
          "id": 18126,
          "amount": 6
        },
        {
          "id": 18117,
          "amount": 6
        },
        {
          "id": 18103,
          "amount": 24
        }
      ]
    }
  },
  "13060": {
    "from": 13040,
    "to": 13060,
    "cost": {
      "coins": 50,
      "items": [
        {
          "id": 18101,
          "amount": 12
        },
        {
          "id": 18110,
          "amount": 9
        },
        {
          "id": 18107,
          "amount": 9
        }
      ]
    }
  },
  "13080": {
    "from": 13060,
    "to": 13080,
    "cost": {
      "coins": 900,
      "items": [
        {
          "id": 18102,
          "amount": 30
        },
        {
          "id": 18111,
          "amount": 40
        },
        {
          "id": 18108,
          "amount": 50
        }
      ]
    }
  },
  "13140": {
    "from": 13040,
    "to": 13140,
    "cost": {
      "coins": 450,
      "items": [
        {
          "id": 18102,
          "amount": 18
        },
        {
          "id": 18111,
          "amount": 15
        },
        {
          "id": 18108,
          "amount": 15
        }
      ]
    }
  },
  "13160": {
    "from": 13140,
    "to": 13160,
    "cost": {
      "coins": 2000,
      "items": [
        {
          "id": 18117,
          "amount": 3
        },
        {
          "id": 18103,
          "amount": 21
        },
        {
          "id": 18109,
          "amount": 21
        }
      ]
    }
  },
  "14160": {
    "from": 14140,
    "to": 14160,
    "cost": {
      "coins": 450,
      "items": [
        {
          "id": 18125,
          "amount": 6
        },
        {
          "id": 18102,
          "amount": 15
        },
        {
          "id": 18111,
          "amount": 15
        }
      ]
    }
  },
  "14180": {
    "from": 14140,
    "to": 14180,
    "cost": {
      "coins": 50,
      "items": [
        {
          "id": 18101,
          "amount": 12
        },
        {
          "id": 18110,
          "amount": 9
        },
        {
          "id": 18104,
          "amount": 9
        }
      ]
    }
  },
  "14240": {
    "from": 14180,
    "to": 14240,
    "cost": {
      "coins": 400,
      "items": [
        {
          "id": 18102,
          "amount": 18
        },
        {
          "id": 18111,
          "amount": 15
        },
        {
          "id": 18105,
          "amount": 15
        }
      ]
    }
  },
  "14260": {
    "from": 14240,
    "to": 14260,
    "cost": {
      "coins": 500,
      "items": [
        {
          "id": 18102,
          "amount": 24
        },
        {
          "id": 18111,
          "amount": 18
        },
        {
          "id": 18105,
          "amount": 18
        }
      ]
    }
  },
  "14340": {
    "from": 14240,
    "to": 14340,
    "cost": {
      "coins": 500,
      "items": [
        {
          "id": 18102,
          "amount": 24
        },
        {
          "id": 18111,
          "amount": 18
        },
        {
          "id": 18105,
          "amount": 18
        }
      ]
    }
  },
  "14360": {
    "from": 14380,
    "to": 14360,
    "cost": {
      "coins": 2000,
      "items": [
        {
          "id": 18126,
          "amount": 6
        },
        {
          "id": 18117,
          "amount": 2
        },
        {
          "id": 18106,
          "amount": 20
        }
      ]
    }
  },
  "14380": {
    "from": 14180,
    "to": 14380,
    "cost": {
      "coins": 400,
      "items": [
        {
          "id": 18102,
          "amount": 18
        },
        {
          "id": 18111,
          "amount": 15
        },
        {
          "id": 18105,
          "amount": 15
        }
      ]
    }
  },
  "14460": {
    "from": 14340,
    "to": 14460,
    "cost": {
      "coins": 12000,
      "items": [
        {
          "id": 18118,
          "amount": 11
        },
        {
          "id": 18103,
          "amount": 64
        },
        {
          "id": 18106,
          "amount": 64
        }
      ]
    }
  },
  "14461": {
    "from": 14360,
    "to": 14460,
    "cost": {
      "coins": 10000,
      "items": [
        {
          "id": 18118,
          "amount": 9
        },
        {
          "id": 18103,
          "amount": 64
        },
        {
          "id": 18109,
          "amount": 54
        }
      ]
    }
  },
  "14500": {
    "from": 14520,
    "to": 14500,
    "cost": {
      "coins": 7500,
      "items": [
        {
          "id": 18127,
          "amount": 6
        },
        {
          "id": 18117,
          "amount": 20
        },
        {
          "id": 18106,
          "amount": 20
        }
      ]
    }
  },
  "14520": {
    "from": 14260,
    "to": 14520,
    "cost": {
      "coins": 4000,
      "items": [
        {
          "id": 18126,
          "amount": 7
        },
        {
          "id": 18117,
          "amount": 10
        },
        {
          "id": 18106,
          "amount": 48
        }
      ]
    }
  },
  "15060": {
    "from": 15040,
    "to": 15060,
    "cost": {
      "coins": 500,
      "items": [
        {
          "id": 18108,
          "amount": 24
        },
        {
          "id": 18105,
          "amount": 18
        },
        {
          "id": 18113,
          "amount": 9
        }
      ]
    }
  },
  "15140": {
    "from": 15040,
    "to": 15140,
    "cost": {
      "coins": 2000,
      "items": [
        {
          "id": 18119,
          "amount": 3
        },
        {
          "id": 18109,
          "amount": 21
        },
        {
          "id": 18114,
          "amount": 21
        }
      ]
    }
  },
  "15160": {
    "from": 15060,
    "to": 15160,
    "cost": {
      "coins": 4000,
      "items": [
        {
          "id": 18119,
          "amount": 9
        },
        {
          "id": 18109,
          "amount": 30
        },
        {
          "id": 18114,
          "amount": 30
        }
      ]
    }
  },
  "15200": {
    "from": 5040,
    "to": 15200,
    "cost": {
      "coins": 50,
      "items": [
        {
          "id": 18107,
          "amount": 12
        },
        {
          "id": 18104,
          "amount": 9
        },
        {
          "id": 18110,
          "amount": 9
        }
      ]
    }
  },
  "15220": {
    "from": 5140,
    "to": 15220,
    "cost": {
      "coins": 500,
      "items": [
        {
          "id": 18108,
          "amount": 24
        },
        {
          "id": 18105,
          "amount": 18
        },
        {
          "id": 18113,
          "amount": 9
        }
      ]
    }
  },
  "15221": {
    "from": 15200,
    "to": 15220,
    "cost": {
      "coins": 900,
      "items": [
        {
          "id": 18108,
          "amount": 30
        },
        {
          "id": 18105,
          "amount": 30
        },
        {
          "id": 18113,
          "amount": 30
        }
      ]
    }
  },
  "15240": {
    "from": 5240,
    "to": 15240,
    "cost": {
      "coins": 2000,
      "items": [
        {
          "id": 18119,
          "amount": 3
        },
        {
          "id": 18109,
          "amount": 21
        },
        {
          "id": 18114,
          "amount": 21
        }
      ]
    }
  },
  "15241": {
    "from": 15220,
    "to": 15240,
    "cost": {
      "coins": 4000,
      "items": [
        {
          "id": 18119,
          "amount": 9
        },
        {
          "id": 18109,
          "amount": 30
        },
        {
          "id": 18114,
          "amount": 30
        }
      ]
    }
  },
  "15300": {
    "from": 15220,
    "to": 15300,
    "cost": {
      "coins": 1500,
      "items": [
        {
          "id": 18119,
          "amount": 3
        },
        {
          "id": 18109,
          "amount": 15
        },
        {
          "id": 18114,
          "amount": 12
        }
      ]
    }
  },
  "16040": {
    "from": 6040,
    "to": 16040,
    "cost": {
      "coins": 50,
      "items": [
        {
          "id": 18104,
          "amount": 12
        },
        {
          "id": 18101,
          "amount": 9
        },
        {
          "id": 18110,
          "amount": 9
        }
      ]
    }
  },
  "16060": {
    "from": 26340,
    "to": 16060,
    "cost": {
      "coins": 500,
      "items": [
        {
          "id": 18105,
          "amount": 24
        },
        {
          "id": 18102,
          "amount": 18
        },
        {
          "id": 18113,
          "amount": 9
        }
      ]
    }
  },
  "16080": {
    "from": 16060,
    "to": 16080,
    "cost": {
      "coins": 4000,
      "items": [
        {
          "id": 18121,
          "amount": 9
        },
        {
          "id": 18106,
          "amount": 45
        },
        {
          "id": 18114,
          "amount": 30
        }
      ]
    }
  },
  "16140": {
    "from": 16040,
    "to": 16140,
    "cost": {
      "coins": 400,
      "items": [
        {
          "id": 18105,
          "amount": 18
        },
        {
          "id": 18102,
          "amount": 12
        },
        {
          "id": 18113,
          "amount": 9
        }
      ]
    }
  },
  "16160": {
    "from": 16140,
    "to": 16160,
    "cost": {
      "coins": 500,
      "items": [
        {
          "id": 18105,
          "amount": 24
        },
        {
          "id": 18102,
          "amount": 18
        },
        {
          "id": 18113,
          "amount": 9
        }
      ]
    }
  },
  "16240": {
    "from": 16140,
    "to": 16240,
    "cost": {
      "coins": 500,
      "items": [
        {
          "id": 18105,
          "amount": 24
        },
        {
          "id": 18102,
          "amount": 18
        },
        {
          "id": 18113,
          "amount": 9
        }
      ]
    }
  },
  "16340": {
    "from": 16140,
    "to": 16340,
    "cost": {
      "coins": 500,
      "items": [
        {
          "id": 18105,
          "amount": 24
        },
        {
          "id": 18102,
          "amount": 18
        },
        {
          "id": 18113,
          "amount": 9
        }
      ]
    }
  },
  "16440": {
    "from": 16160,
    "to": 16440,
    "cost": {
      "coins": 1500,
      "items": [
        {
          "id": 18121,
          "amount": 3
        },
        {
          "id": 18106,
          "amount": 15
        },
        {
          "id": 18114,
          "amount": 12
        }
      ]
    }
  },
  "16441": {
    "from": 16240,
    "to": 16440,
    "cost": {
      "coins": 1500,
      "items": [
        {
          "id": 18121,
          "amount": 3
        },
        {
          "id": 18106,
          "amount": 15
        },
        {
          "id": 18114,
          "amount": 12
        }
      ]
    }
  },
  "16442": {
    "from": 16340,
    "to": 16440,
    "cost": {
      "coins": 1500,
      "items": [
        {
          "id": 18121,
          "amount": 3
        },
        {
          "id": 18106,
          "amount": 15
        },
        {
          "id": 18114,
          "amount": 12
        }
      ]
    }
  },
  "16460": {
    "from": 11240,
    "to": 16460,
    "cost": {
      "coins": 5000,
      "items": [
        {
          "id": 18121,
          "amount": 9
        },
        {
          "id": 18106,
          "amount": 21
        },
        {
          "id": 18114,
          "amount": 24
        }
      ]
    }
  },
  "16480": {
    "from": 16080,
    "to": 16480,
    "cost": {
      "coins": 7500,
      "items": [
        {
          "id": 18122,
          "amount": 9
        },
        {
          "id": 18106,
          "amount": 36
        },
        {
          "id": 18103,
          "amount": 36
        }
      ]
    }
  },
  "17080": {
    "from": 17040,
    "to": 17080,
    "cost": {
      "coins": 450,
      "items": [
        {
          "id": 18105,
          "amount": 18
        },
        {
          "id": 18111,
          "amount": 12
        },
        {
          "id": 18115,
          "amount": 9
        }
      ]
    }
  },
  "17140": {
    "from": 17040,
    "to": 17140,
    "cost": {
      "coins": 450,
      "items": [
        {
          "id": 18105,
          "amount": 18
        },
        {
          "id": 18111,
          "amount": 12
        },
        {
          "id": 18115,
          "amount": 9
        }
      ]
    }
  },
  "17240": {
    "from": 17040,
    "to": 17240,
    "cost": {
      "coins": 450,
      "items": [
        {
          "id": 18105,
          "amount": 18
        },
        {
          "id": 18111,
          "amount": 12
        },
        {
          "id": 18115,
          "amount": 9
        }
      ]
    }
  },
  "17340": {
    "from": 17140,
    "to": 17340,
    "cost": {
      "coins": 2000,
      "items": [
        {
          "id": 18123,
          "amount": 3
        },
        {
          "id": 18106,
          "amount": 21
        },
        {
          "id": 18116,
          "amount": 21
        }
      ]
    }
  },
  "17360": {
    "from": 17340,
    "to": 17360,
    "cost": {
      "coins": 2500,
      "items": [
        {
          "id": 18123,
          "amount": 9
        },
        {
          "id": 18106,
          "amount": 21
        },
        {
          "id": 18116,
          "amount": 21
        }
      ]
    }
  },
  "17380": {
    "from": 17340,
    "to": 17380,
    "cost": {
      "coins": 2500,
      "items": [
        {
          "id": 18123,
          "amount": 9
        },
        {
          "id": 18106,
          "amount": 21
        },
        {
          "id": 18116,
          "amount": 21
        }
      ]
    }
  },
  "17400": {
    "from": 17140,
    "to": 17400,
    "cost": {
      "coins": 500,
      "items": [
        {
          "id": 18105,
          "amount": 24
        },
        {
          "id": 18111,
          "amount": 18
        },
        {
          "id": 18115,
          "amount": 9
        }
      ]
    }
  },
  "17420": {
    "from": 17240,
    "to": 17420,
    "cost": {
      "coins": 2000,
      "items": [
        {
          "id": 18126,
          "amount": 6
        },
        {
          "id": 18123,
          "amount": 2
        },
        {
          "id": 18106,
          "amount": 20
        }
      ]
    }
  },
  "18140": {
    "from": 18040,
    "to": 18140,
    "cost": {
      "coins": 450,
      "items": [
        {
          "id": 18105,
          "amount": 18
        },
        {
          "id": 18108,
          "amount": 12
        },
        {
          "id": 18115,
          "amount": 9
        }
      ]
    }
  },
  "18220": {
    "from": 19240,
    "to": 18220,
    "cost": {
      "coins": 2500,
      "items": [
        {
          "id": 18123,
          "amount": 9
        },
        {
          "id": 18106,
          "amount": 21
        },
        {
          "id": 18116,
          "amount": 18
        }
      ]
    }
  },
  "18221": {
    "from": 18140,
    "to": 18220,
    "cost": {
      "coins": 4500,
      "items": [
        {
          "id": 18123,
          "amount": 9
        },
        {
          "id": 18106,
          "amount": 48
        },
        {
          "id": 18116,
          "amount": 36
        }
      ]
    }
  },
  "19040": {
    "from": 18040,
    "to": 19040,
    "cost": {
      "coins": 50,
      "items": [
        {
          "id": 18104,
          "amount": 12
        },
        {
          "id": 18107,
          "amount": 9
        },
        {
          "id": 18101,
          "amount": 9
        }
      ]
    }
  },
  "19140": {
    "from": 19040,
    "to": 19140,
    "cost": {
      "coins": 400,
      "items": [
        {
          "id": 18105,
          "amount": 18
        },
        {
          "id": 18108,
          "amount": 12
        },
        {
          "id": 18115,
          "amount": 9
        }
      ]
    }
  },
  "19160": {
    "from": 19140,
    "to": 19160,
    "cost": {
      "coins": 2000,
      "items": [
        {
          "id": 18126,
          "amount": 6
        },
        {
          "id": 18123,
          "amount": 2
        },
        {
          "id": 18106,
          "amount": 20
        }
      ]
    }
  },
  "19240": {
    "from": 19140,
    "to": 19240,
    "cost": {
      "coins": 2000,
      "items": [
        {
          "id": 18123,
          "amount": 3
        },
        {
          "id": 18106,
          "amount": 21
        },
        {
          "id": 18116,
          "amount": 18
        }
      ]
    }
  },
  "21140": {
    "from": 21040,
    "to": 21140,
    "cost": {
      "coins": 50,
      "items": [
        {
          "id": 18101,
          "amount": 12
        },
        {
          "id": 18110,
          "amount": 9
        },
        {
          "id": 18107,
          "amount": 9
        }
      ]
    }
  },
  "21160": {
    "from": 21140,
    "to": 21160,
    "cost": {
      "coins": 400,
      "items": [
        {
          "id": 18102,
          "amount": 18
        },
        {
          "id": 18111,
          "amount": 15
        },
        {
          "id": 18108,
          "amount": 15
        }
      ]
    }
  },
  "21240": {
    "from": 21140,
    "to": 21240,
    "cost": {
      "coins": 400,
      "items": [
        {
          "id": 18102,
          "amount": 18
        },
        {
          "id": 18111,
          "amount": 15
        },
        {
          "id": 18108,
          "amount": 15
        }
      ]
    }
  },
  "21340": {
    "from": 21040,
    "to": 21340,
    "cost": {
      "coins": 50,
      "items": [
        {
          "id": 18101,
          "amount": 12
        },
        {
          "id": 18110,
          "amount": 9
        },
        {
          "id": 18107,
          "amount": 9
        }
      ]
    }
  },
  "21440": {
    "from": 21340,
    "to": 21440,
    "cost": {
      "coins": 400,
      "items": [
        {
          "id": 18102,
          "amount": 18
        },
        {
          "id": 18111,
          "amount": 15
        },
        {
          "id": 18108,
          "amount": 15
        }
      ]
    }
  },
  "21460": {
    "from": 21440,
    "to": 21460,
    "cost": {
      "coins": 2000,
      "items": [
        {
          "id": 18117,
          "amount": 3
        },
        {
          "id": 18112,
          "amount": 21
        },
        {
          "id": 18109,
          "amount": 21
        }
      ]
    }
  },
  "21540": {
    "from": 21440,
    "to": 21540,
    "cost": {
      "coins": 500,
      "items": [
        {
          "id": 18102,
          "amount": 24
        },
        {
          "id": 18111,
          "amount": 18
        },
        {
          "id": 18108,
          "amount": 18
        }
      ]
    }
  },
  "21600": {
    "from": 21460,
    "to": 21600,
    "cost": {
      "coins": 2500,
      "items": [
        {
          "id": 18117,
          "amount": 9
        },
        {
          "id": 18103,
          "amount": 18
        },
        {
          "id": 18109,
          "amount": 21
        }
      ]
    }
  },
  "21620": {
    "from": 21340,
    "to": 21620,
    "cost": {
      "coins": 2400,
      "items": [
        {
          "id": 18117,
          "amount": 3
        },
        {
          "id": 18106,
          "amount": 24
        },
        {
          "id": 18109,
          "amount": 30
        }
      ]
    }
  },
  "22060": {
    "from": 22040,
    "to": 22060,
    "cost": {
      "coins": 50,
      "items": [
        {
          "id": 18101,
          "amount": 12
        },
        {
          "id": 18110,
          "amount": 9
        },
        {
          "id": 18107,
          "amount": 9
        }
      ]
    }
  },
  "22140": {
    "from": 22060,
    "to": 22140,
    "cost": {
      "coins": 400,
      "items": [
        {
          "id": 18102,
          "amount": 18
        },
        {
          "id": 18111,
          "amount": 15
        },
        {
          "id": 18108,
          "amount": 15
        }
      ]
    }
  },
  "22240": {
    "from": 22060,
    "to": 22240,
    "cost": {
      "coins": 400,
      "items": [
        {
          "id": 18102,
          "amount": 18
        },
        {
          "id": 18111,
          "amount": 15
        },
        {
          "id": 18108,
          "amount": 15
        }
      ]
    }
  },
  "22260": {
    "from": 22240,
    "to": 22260,
    "cost": {
      "coins": 4500,
      "items": [
        {
          "id": 18126,
          "amount": 8
        },
        {
          "id": 18117,
          "amount": 4
        },
        {
          "id": 18103,
          "amount": 72
        }
      ]
    }
  },
  "23100": {
    "from": 23200,
    "to": 23100,
    "cost": {
      "coins": 2500,
      "items": [
        {
          "id": 18126,
          "amount": 6
        },
        {
          "id": 18117,
          "amount": 6
        },
        {
          "id": 18103,
          "amount": 24
        }
      ]
    }
  },
  "23120": {
    "from": 23100,
    "to": 23120,
    "cost": {
      "coins": 7500,
      "items": [
        {
          "id": 18127,
          "amount": 6
        },
        {
          "id": 18117,
          "amount": 20
        },
        {
          "id": 18106,
          "amount": 20
        }
      ]
    }
  },
  "23200": {
    "from": 23040,
    "to": 23200,
    "cost": {
      "coins": 2000,
      "items": [
        {
          "id": 18126,
          "amount": 6
        },
        {
          "id": 18117,
          "amount": 2
        },
        {
          "id": 18103,
          "amount": 21
        }
      ]
    }
  },
  "23220": {
    "from": 23200,
    "to": 23220,
    "cost": {
      "coins": 2500,
      "items": [
        {
          "id": 18126,
          "amount": 6
        },
        {
          "id": 18117,
          "amount": 6
        },
        {
          "id": 18103,
          "amount": 24
        }
      ]
    }
  },
  "24040": {
    "from": 24060,
    "to": 24040,
    "cost": {
      "coins": 1500,
      "items": [
        {
          "id": 18117,
          "amount": 3
        },
        {
          "id": 18103,
          "amount": 15
        },
        {
          "id": 18109,
          "amount": 15
        }
      ]
    }
  },
  "24060": {
    "from": 24140,
    "to": 24060,
    "cost": {
      "coins": 500,
      "items": [
        {
          "id": 18102,
          "amount": 24
        },
        {
          "id": 18111,
          "amount": 18
        },
        {
          "id": 18108,
          "amount": 18
        }
      ]
    }
  },
  "24160": {
    "from": 24240,
    "to": 24160,
    "cost": {
      "coins": 2500,
      "items": [
        {
          "id": 18126,
          "amount": 6
        },
        {
          "id": 18117,
          "amount": 6
        },
        {
          "id": 18106,
          "amount": 24
        }
      ]
    }
  },
  "24240": {
    "from": 24140,
    "to": 24240,
    "cost": {
      "coins": 2000,
      "items": [
        {
          "id": 18117,
          "amount": 3
        },
        {
          "id": 18103,
          "amount": 21
        },
        {
          "id": 18106,
          "amount": 21
        }
      ]
    }
  },
  "24340": {
    "from": 24140,
    "to": 24340,
    "cost": {
      "coins": 2000,
      "items": [
        {
          "id": 18117,
          "amount": 3
        },
        {
          "id": 18103,
          "amount": 24
        },
        {
          "id": 18106,
          "amount": 18
        }
      ]
    }
  },
  "25000": {
    "from": 5040,
    "to": 25000,
    "cost": {
      "coins": 50,
      "items": [
        {
          "id": 18107,
          "amount": 12
        },
        {
          "id": 18104,
          "amount": 9
        },
        {
          "id": 18110,
          "amount": 9
        }
      ]
    }
  },
  "25020": {
    "from": 5140,
    "to": 25020,
    "cost": {
      "coins": 500,
      "items": [
        {
          "id": 18108,
          "amount": 24
        },
        {
          "id": 18105,
          "amount": 18
        },
        {
          "id": 18113,
          "amount": 12
        }
      ]
    }
  },
  "25021": {
    "from": 25000,
    "to": 25020,
    "cost": {
      "coins": 900,
      "items": [
        {
          "id": 18108,
          "amount": 30
        },
        {
          "id": 18105,
          "amount": 30
        },
        {
          "id": 18113,
          "amount": 24
        }
      ]
    }
  },
  "25040": {
    "from": 5240,
    "to": 25040,
    "cost": {
      "coins": 2500,
      "items": [
        {
          "id": 18119,
          "amount": 9
        },
        {
          "id": 18109,
          "amount": 21
        },
        {
          "id": 18114,
          "amount": 18
        }
      ]
    }
  },
  "25041": {
    "from": 25020,
    "to": 25040,
    "cost": {
      "coins": 4000,
      "items": [
        {
          "id": 18119,
          "amount": 9
        },
        {
          "id": 18109,
          "amount": 36
        },
        {
          "id": 18114,
          "amount": 30
        }
      ]
    }
  },
  "25200": {
    "from": 25140,
    "to": 25200,
    "cost": {
      "coins": 2000,
      "items": [
        {
          "id": 18119,
          "amount": 3
        },
        {
          "id": 18109,
          "amount": 21
        },
        {
          "id": 18114,
          "amount": 18
        }
      ]
    }
  },
  "25300": {
    "from": 25140,
    "to": 25300,
    "cost": {
      "coins": 2000,
      "items": [
        {
          "id": 18119,
          "amount": 3
        },
        {
          "id": 18109,
          "amount": 21
        },
        {
          "id": 18114,
          "amount": 18
        }
      ]
    }
  },
  "26040": {
    "from": 6040,
    "to": 26040,
    "cost": {
      "coins": 50,
      "items": [
        {
          "id": 18104,
          "amount": 12
        },
        {
          "id": 18101,
          "amount": 9
        },
        {
          "id": 18110,
          "amount": 9
        }
      ]
    }
  },
  "26060": {
    "from": 26040,
    "to": 26060,
    "cost": {
      "coins": 400,
      "items": [
        {
          "id": 18105,
          "amount": 18
        },
        {
          "id": 18102,
          "amount": 12
        },
        {
          "id": 18113,
          "amount": 9
        }
      ]
    }
  },
  "26140": {
    "from": 26040,
    "to": 26140,
    "cost": {
      "coins": 400,
      "items": [
        {
          "id": 18105,
          "amount": 18
        },
        {
          "id": 18102,
          "amount": 12
        },
        {
          "id": 18113,
          "amount": 9
        }
      ]
    }
  },
  "26240": {
    "from": 26140,
    "to": 26240,
    "cost": {
      "coins": 2000,
      "items": [
        {
          "id": 18121,
          "amount": 3
        },
        {
          "id": 18106,
          "amount": 21
        },
        {
          "id": 18114,
          "amount": 18
        }
      ]
    }
  },
  "26340": {
    "from": 6040,
    "to": 26340,
    "cost": {
      "coins": 450,
      "items": [
        {
          "id": 18105,
          "amount": 18
        },
        {
          "id": 18102,
          "amount": 12
        },
        {
          "id": 18113,
          "amount": 9
        }
      ]
    }
  },
  "26360": {
    "from": 6040,
    "to": 26360,
    "cost": {
      "coins": 450,
      "items": [
        {
          "id": 18105,
          "amount": 18
        },
        {
          "id": 18102,
          "amount": 12
        },
        {
          "id": 18113,
          "amount": 9
        }
      ]
    }
  },
  "26380": {
    "from": 26360,
    "to": 26380,
    "cost": {
      "coins": 500,
      "items": [
        {
          "id": 18105,
          "amount": 24
        },
        {
          "id": 18102,
          "amount": 18
        },
        {
          "id": 18113,
          "amount": 9
        }
      ]
    }
  },
  "26440": {
    "from": 26040,
    "to": 26440,
    "cost": {
      "coins": 400,
      "items": [
        {
          "id": 18105,
          "amount": 18
        },
        {
          "id": 18102,
          "amount": 12
        },
        {
          "id": 18113,
          "amount": 9
        }
      ]
    }
  },
  "26460": {
    "from": 26440,
    "to": 26460,
    "cost": {
      "coins": 500,
      "items": [
        {
          "id": 18105,
          "amount": 24
        },
        {
          "id": 18102,
          "amount": 18
        },
        {
          "id": 18113,
          "amount": 9
        }
      ]
    }
  },
  "26540": {
    "from": 26440,
    "to": 26540,
    "cost": {
      "coins": 2000,
      "items": [
        {
          "id": 18121,
          "amount": 3
        },
        {
          "id": 18106,
          "amount": 21
        },
        {
          "id": 18114,
          "amount": 18
        }
      ]
    }
  },
  "26600": {
    "from": 26620,
    "to": 26600,
    "cost": {
      "coins": 2500,
      "items": [
        {
          "id": 18121,
          "amount": 9
        },
        {
          "id": 18106,
          "amount": 21
        },
        {
          "id": 18114,
          "amount": 18
        }
      ]
    }
  },
  "26620": {
    "from": 26060,
    "to": 26620,
    "cost": {
      "coins": 2000,
      "items": [
        {
          "id": 18121,
          "amount": 3
        },
        {
          "id": 18106,
          "amount": 21
        },
        {
          "id": 18114,
          "amount": 18
        }
      ]
    }
  },
  "26640": {
    "from": 26460,
    "to": 26640,
    "cost": {
      "coins": 1500,
      "items": [
        {
          "id": 18121,
          "amount": 3
        },
        {
          "id": 18106,
          "amount": 15
        },
        {
          "id": 18114,
          "amount": 12
        }
      ]
    }
  },
  "26660": {
    "from": 26060,
    "to": 26660,
    "cost": {
      "coins": 2000,
      "items": [
        {
          "id": 18121,
          "amount": 3
        },
        {
          "id": 18106,
          "amount": 21
        },
        {
          "id": 18114,
          "amount": 18
        }
      ]
    }
  },
  "26680": {
    "from": 26640,
    "to": 26680,
    "cost": {
      "coins": 5000,
      "items": [
        {
          "id": 18121,
          "amount": 9
        },
        {
          "id": 18106,
          "amount": 21
        },
        {
          "id": 18114,
          "amount": 24
        }
      ]
    }
  },
  "27040": {
    "from": 27260,
    "to": 27040,
    "cost": {
      "coins": 400,
      "items": [
        {
          "id": 18105,
          "amount": 18
        },
        {
          "id": 18111,
          "amount": 12
        },
        {
          "id": 18115,
          "amount": 9
        }
      ]
    }
  },
  "27060": {
    "from": 27040,
    "to": 27060,
    "cost": {
      "coins": 2000,
      "items": [
        {
          "id": 18123,
          "amount": 3
        },
        {
          "id": 18106,
          "amount": 21
        },
        {
          "id": 18116,
          "amount": 18
        }
      ]
    }
  },
  "27140": {
    "from": 27040,
    "to": 27140,
    "cost": {
      "coins": 2000,
      "items": [
        {
          "id": 18123,
          "amount": 3
        },
        {
          "id": 18106,
          "amount": 21
        },
        {
          "id": 18116,
          "amount": 18
        }
      ]
    }
  },
  "27260": {
    "from": 27240,
    "to": 27260,
    "cost": {
      "coins": 50,
      "items": [
        {
          "id": 18104,
          "amount": 12
        },
        {
          "id": 18110,
          "amount": 9
        },
        {
          "id": 18101,
          "amount": 9
        }
      ]
    }
  },
  "27300": {
    "from": 27260,
    "to": 27300,
    "cost": {
      "coins": 2400,
      "items": [
        {
          "id": 18123,
          "amount": 3
        },
        {
          "id": 18106,
          "amount": 24
        },
        {
          "id": 18116,
          "amount": 24
        }
      ]
    }
  },
  "27320": {
    "from": 27060,
    "to": 27320,
    "cost": {
      "coins": 2500,
      "items": [
        {
          "id": 18123,
          "amount": 9
        },
        {
          "id": 18106,
          "amount": 21
        },
        {
          "id": 18116,
          "amount": 18
        }
      ]
    }
  },
  "28040": {
    "from": 29040,
    "to": 28040,
    "cost": {
      "coins": 450,
      "items": [
        {
          "id": 18105,
          "amount": 18
        },
        {
          "id": 18108,
          "amount": 12
        },
        {
          "id": 18115,
          "amount": 9
        }
      ]
    }
  },
  "28140": {
    "from": 28340,
    "to": 28140,
    "cost": {
      "coins": 1500,
      "items": [
        {
          "id": 18123,
          "amount": 3
        },
        {
          "id": 18106,
          "amount": 15
        },
        {
          "id": 18116,
          "amount": 12
        }
      ]
    }
  },
  "28200": {
    "from": 29140,
    "to": 28200,
    "cost": {
      "coins": 2000,
      "items": [
        {
          "id": 18123,
          "amount": 3
        },
        {
          "id": 18106,
          "amount": 21
        },
        {
          "id": 18116,
          "amount": 18
        }
      ]
    }
  },
  "28220": {
    "from": 28200,
    "to": 28220,
    "cost": {
      "coins": 2500,
      "items": [
        {
          "id": 18123,
          "amount": 9
        },
        {
          "id": 18106,
          "amount": 21
        },
        {
          "id": 18116,
          "amount": 18
        }
      ]
    }
  },
  "28340": {
    "from": 28040,
    "to": 28340,
    "cost": {
      "coins": 500,
      "items": [
        {
          "id": 18105,
          "amount": 24
        },
        {
          "id": 18108,
          "amount": 18
        },
        {
          "id": 18115,
          "amount": 9
        }
      ]
    }
  },
  "28400": {
    "from": 28220,
    "to": 28400,
    "cost": {
      "coins": 7500,
      "items": [
        {
          "id": 18124,
          "amount": 9
        },
        {
          "id": 18106,
          "amount": 36
        },
        {
          "id": 18116,
          "amount": 30
        }
      ]
    }
  },
  "28420": {
    "from": 28140,
    "to": 28420,
    "cost": {
      "coins": 10000,
      "items": [
        {
          "id": 18127,
          "amount": 9
        },
        {
          "id": 18123,
          "amount": 20
        },
        {
          "id": 18106,
          "amount": 20
        }
      ]
    }
  },
  "29140": {
    "from": 29040,
    "to": 29140,
    "cost": {
      "coins": 450,
      "items": [
        {
          "id": 18105,
          "amount": 18
        },
        {
          "id": 18108,
          "amount": 12
        },
        {
          "id": 18115,
          "amount": 9
        }
      ]
    }
  },
  "29200": {
    "from": 29140,
    "to": 29200,
    "cost": {
      "coins": 2000,
      "items": [
        {
          "id": 18123,
          "amount": 3
        },
        {
          "id": 18106,
          "amount": 21
        },
        {
          "id": 18116,
          "amount": 18
        }
      ]
    }
  },
  "31040": {
    "from": 31060,
    "to": 31040,
    "cost": {
      "coins": 2000,
      "items": [
        {
          "id": 18117,
          "amount": 3
        },
        {
          "id": 18112,
          "amount": 21
        },
        {
          "id": 18109,
          "amount": 21
        }
      ]
    }
  },
  "31060": {
    "from": 31260,
    "to": 31060,
    "cost": {
      "coins": 400,
      "items": [
        {
          "id": 18102,
          "amount": 18
        },
        {
          "id": 18111,
          "amount": 15
        },
        {
          "id": 18108,
          "amount": 15
        }
      ]
    }
  },
  "31080": {
    "from": 31040,
    "to": 31080,
    "cost": {
      "coins": 10000,
      "items": [
        {
          "id": 18118,
          "amount": 9
        },
        {
          "id": 18112,
          "amount": 64
        },
        {
          "id": 18109,
          "amount": 54
        }
      ]
    }
  },
  "31160": {
    "from": 31140,
    "to": 31160,
    "cost": {
      "coins": 50,
      "items": [
        {
          "id": 18101,
          "amount": 12
        },
        {
          "id": 18110,
          "amount": 9
        },
        {
          "id": 18107,
          "amount": 9
        }
      ]
    }
  },
  "31180": {
    "from": 31160,
    "to": 31180,
    "cost": {
      "coins": 400,
      "items": [
        {
          "id": 18102,
          "amount": 18
        },
        {
          "id": 18111,
          "amount": 15
        },
        {
          "id": 18108,
          "amount": 15
        }
      ]
    }
  },
  "31240": {
    "from": 31260,
    "to": 31240,
    "cost": {
      "coins": 400,
      "items": [
        {
          "id": 18102,
          "amount": 18
        },
        {
          "id": 18111,
          "amount": 15
        },
        {
          "id": 18108,
          "amount": 15
        }
      ]
    }
  },
  "31260": {
    "from": 31140,
    "to": 31260,
    "cost": {
      "coins": 50,
      "items": [
        {
          "id": 18101,
          "amount": 12
        },
        {
          "id": 18110,
          "amount": 9
        },
        {
          "id": 18107,
          "amount": 9
        }
      ]
    }
  },
  "31280": {
    "from": 31240,
    "to": 31280,
    "cost": {
      "coins": 500,
      "items": [
        {
          "id": 18102,
          "amount": 24
        },
        {
          "id": 18111,
          "amount": 18
        },
        {
          "id": 18108,
          "amount": 18
        }
      ]
    }
  },
  "31300": {
    "from": 31280,
    "to": 31300,
    "cost": {
      "coins": 4000,
      "items": [
        {
          "id": 18117,
          "amount": 9
        },
        {
          "id": 18103,
          "amount": 24
        },
        {
          "id": 18109,
          "amount": 54
        }
      ]
    }
  },
  "32060": {
    "from": 32040,
    "to": 32060,
    "cost": {
      "coins": 50,
      "items": [
        {
          "id": 18101,
          "amount": 12
        },
        {
          "id": 18110,
          "amount": 9
        },
        {
          "id": 18107,
          "amount": 9
        }
      ]
    }
  },
  "32140": {
    "from": 32040,
    "to": 32140,
    "cost": {
      "coins": 450,
      "items": [
        {
          "id": 18102,
          "amount": 18
        },
        {
          "id": 18111,
          "amount": 15
        },
        {
          "id": 18108,
          "amount": 15
        }
      ]
    }
  },
  "32240": {
    "from": 32340,
    "to": 32240,
    "cost": {
      "coins": 2000,
      "items": [
        {
          "id": 18117,
          "amount": 3
        },
        {
          "id": 18103,
          "amount": 21
        },
        {
          "id": 18109,
          "amount": 21
        }
      ]
    }
  },
  "32260": {
    "from": 32240,
    "to": 32260,
    "cost": {
      "coins": 2500,
      "items": [
        {
          "id": 18126,
          "amount": 6
        },
        {
          "id": 18117,
          "amount": 6
        },
        {
          "id": 18103,
          "amount": 24
        }
      ]
    }
  },
  "32340": {
    "from": 32060,
    "to": 32340,
    "cost": {
      "coins": 400,
      "items": [
        {
          "id": 18102,
          "amount": 18
        },
        {
          "id": 18111,
          "amount": 15
        },
        {
          "id": 18108,
          "amount": 15
        }
      ]
    }
  },
  "33060": {
    "from": 33080,
    "to": 33060,
    "cost": {
      "coins": 1500,
      "items": [
        {
          "id": 18126,
          "amount": 6
        },
        {
          "id": 18117,
          "amount": 2
        },
        {
          "id": 18103,
          "amount": 8
        }
      ]
    }
  },
  "33080": {
    "from": 33040,
    "to": 33080,
    "cost": {
      "coins": 500,
      "items": [
        {
          "id": 18102,
          "amount": 24
        },
        {
          "id": 18111,
          "amount": 18
        },
        {
          "id": 18108,
          "amount": 18
        }
      ]
    }
  },
  "33100": {
    "from": 34300,
    "to": 33100,
    "cost": {
      "coins": 4000,
      "items": [
        {
          "id": 18126,
          "amount": 7
        },
        {
          "id": 18117,
          "amount": 10
        },
        {
          "id": 18106,
          "amount": 48
        }
      ]
    }
  },
  "34060": {
    "from": 34040,
    "to": 34060,
    "cost": {
      "coins": 50,
      "items": [
        {
          "id": 18101,
          "amount": 12
        },
        {
          "id": 18110,
          "amount": 9
        },
        {
          "id": 18104,
          "amount": 9
        }
      ]
    }
  },
  "34140": {
    "from": 34060,
    "to": 34140,
    "cost": {
      "coins": 400,
      "items": [
        {
          "id": 18102,
          "amount": 18
        },
        {
          "id": 18111,
          "amount": 15
        },
        {
          "id": 18105,
          "amount": 15
        }
      ]
    }
  },
  "34160": {
    "from": 34140,
    "to": 34160,
    "cost": {
      "coins": 2000,
      "items": [
        {
          "id": 18117,
          "amount": 3
        },
        {
          "id": 18103,
          "amount": 21
        },
        {
          "id": 18106,
          "amount": 21
        }
      ]
    }
  },
  "34180": {
    "from": 34300,
    "to": 34180,
    "cost": {
      "coins": 1500,
      "items": [
        {
          "id": 18126,
          "amount": 6
        },
        {
          "id": 18117,
          "amount": 2
        },
        {
          "id": 18106,
          "amount": 8
        }
      ]
    }
  },
  "34300": {
    "from": 34140,
    "to": 34300,
    "cost": {
      "coins": 500,
      "items": [
        {
          "id": 18102,
          "amount": 24
        },
        {
          "id": 18111,
          "amount": 18
        },
        {
          "id": 18105,
          "amount": 18
        }
      ]
    }
  },
  "35140": {
    "from": 35040,
    "to": 35140,
    "cost": {
      "coins": 450,
      "items": [
        {
          "id": 18108,
          "amount": 18
        },
        {
          "id": 18105,
          "amount": 12
        },
        {
          "id": 18113,
          "amount": 9
        }
      ]
    }
  },
  "35160": {
    "from": 35140,
    "to": 35160,
    "cost": {
      "coins": 500,
      "items": [
        {
          "id": 18108,
          "amount": 24
        },
        {
          "id": 18105,
          "amount": 18
        },
        {
          "id": 18113,
          "amount": 9
        }
      ]
    }
  },
  "35240": {
    "from": 35160,
    "to": 35240,
    "cost": {
      "coins": 1500,
      "items": [
        {
          "id": 18119,
          "amount": 3
        },
        {
          "id": 18109,
          "amount": 15
        },
        {
          "id": 18114,
          "amount": 12
        }
      ]
    }
  },
  "35260": {
    "from": 35240,
    "to": 35260,
    "cost": {
      "coins": 2500,
      "items": [
        {
          "id": 18119,
          "amount": 9
        },
        {
          "id": 18109,
          "amount": 21
        },
        {
          "id": 18114,
          "amount": 18
        }
      ]
    }
  },
  "35340": {
    "from": 35260,
    "to": 35340,
    "cost": {
      "coins": 7500,
      "items": [
        {
          "id": 18120,
          "amount": 9
        },
        {
          "id": 18109,
          "amount": 36
        },
        {
          "id": 18114,
          "amount": 30
        }
      ]
    }
  },
  "35460": {
    "from": 35440,
    "to": 35460,
    "cost": {
      "coins": 500,
      "items": [
        {
          "id": 18108,
          "amount": 24
        },
        {
          "id": 18105,
          "amount": 18
        },
        {
          "id": 18113,
          "amount": 9
        }
      ]
    }
  },
  "35540": {
    "from": 35440,
    "to": 35540,
    "cost": {
      "coins": 2000,
      "items": [
        {
          "id": 18119,
          "amount": 3
        },
        {
          "id": 18109,
          "amount": 21
        },
        {
          "id": 18114,
          "amount": 18
        }
      ]
    }
  },
  "35560": {
    "from": 35540,
    "to": 35560,
    "cost": {
      "coins": 2500,
      "items": [
        {
          "id": 18119,
          "amount": 9
        },
        {
          "id": 18109,
          "amount": 21
        },
        {
          "id": 18114,
          "amount": 18
        }
      ]
    }
  },
  "35580": {
    "from": 35540,
    "to": 35580,
    "cost": {
      "coins": 10000,
      "items": [
        {
          "id": 18120,
          "amount": 9
        },
        {
          "id": 18109,
          "amount": 60
        },
        {
          "id": 18114,
          "amount": 48
        }
      ]
    }
  },
  "36240": {
    "from": 36140,
    "to": 36240,
    "cost": {
      "coins": 450,
      "items": [
        {
          "id": 18105,
          "amount": 18
        },
        {
          "id": 18102,
          "amount": 12
        },
        {
          "id": 18113,
          "amount": 9
        }
      ]
    }
  },
  "36340": {
    "from": 36240,
    "to": 36340,
    "cost": {
      "coins": 500,
      "items": [
        {
          "id": 18105,
          "amount": 24
        },
        {
          "id": 18102,
          "amount": 18
        },
        {
          "id": 18113,
          "amount": 9
        }
      ]
    }
  },
  "36360": {
    "from": 36340,
    "to": 36360,
    "cost": {
      "coins": 1500,
      "items": [
        {
          "id": 18121,
          "amount": 3
        },
        {
          "id": 18106,
          "amount": 15
        },
        {
          "id": 18114,
          "amount": 12
        }
      ]
    }
  },
  "36440": {
    "from": 36140,
    "to": 36440,
    "cost": {
      "coins": 450,
      "items": [
        {
          "id": 18105,
          "amount": 18
        },
        {
          "id": 18102,
          "amount": 12
        },
        {
          "id": 18113,
          "amount": 9
        }
      ]
    }
  },
  "36540": {
    "from": 36140,
    "to": 36540,
    "cost": {
      "coins": 450,
      "items": [
        {
          "id": 18105,
          "amount": 18
        },
        {
          "id": 18102,
          "amount": 12
        },
        {
          "id": 18113,
          "amount": 9
        }
      ]
    }
  },
  "36580": {
    "from": 36540,
    "to": 36580,
    "cost": {
      "coins": 500,
      "items": [
        {
          "id": 18105,
          "amount": 24
        },
        {
          "id": 18102,
          "amount": 18
        },
        {
          "id": 18113,
          "amount": 9
        }
      ]
    }
  },
  "36640": {
    "from": 36540,
    "to": 36640,
    "cost": {
      "coins": 500,
      "items": [
        {
          "id": 18105,
          "amount": 24
        },
        {
          "id": 18102,
          "amount": 18
        },
        {
          "id": 18113,
          "amount": 9
        }
      ]
    }
  },
  "36660": {
    "from": 36640,
    "to": 36660,
    "cost": {
      "coins": 1500,
      "items": [
        {
          "id": 18121,
          "amount": 3
        },
        {
          "id": 18106,
          "amount": 15
        },
        {
          "id": 18114,
          "amount": 12
        }
      ]
    }
  },
  "36700": {
    "from": 36440,
    "to": 36700,
    "cost": {
      "coins": 4500,
      "items": [
        {
          "id": 18126,
          "amount": 8
        },
        {
          "id": 18121,
          "amount": 10
        },
        {
          "id": 18114,
          "amount": 48
        }
      ]
    }
  },
  "36720": {
    "from": 36660,
    "to": 36720,
    "cost": {
      "coins": 5000,
      "items": [
        {
          "id": 18121,
          "amount": 9
        },
        {
          "id": 18106,
          "amount": 21
        },
        {
          "id": 18114,
          "amount": 24
        }
      ]
    }
  },
  "36740": {
    "from": 36580,
    "to": 36740,
    "cost": {
      "coins": 2400,
      "items": [
        {
          "id": 18121,
          "amount": 3
        },
        {
          "id": 18106,
          "amount": 15
        },
        {
          "id": 18114,
          "amount": 12
        }
      ]
    }
  },
  "37140": {
    "from": 37040,
    "to": 37140,
    "cost": {
      "coins": 450,
      "items": [
        {
          "id": 18105,
          "amount": 18
        },
        {
          "id": 18111,
          "amount": 12
        },
        {
          "id": 18115,
          "amount": 9
        }
      ]
    }
  },
  "37160": {
    "from": 37140,
    "to": 37160,
    "cost": {
      "coins": 500,
      "items": [
        {
          "id": 18105,
          "amount": 24
        },
        {
          "id": 18111,
          "amount": 18
        },
        {
          "id": 18115,
          "amount": 9
        }
      ]
    }
  },
  "37240": {
    "from": 37160,
    "to": 37240,
    "cost": {
      "coins": 1500,
      "items": [
        {
          "id": 18123,
          "amount": 3
        },
        {
          "id": 18106,
          "amount": 15
        },
        {
          "id": 18116,
          "amount": 12
        }
      ]
    }
  },
  "37340": {
    "from": 37160,
    "to": 37340,
    "cost": {
      "coins": 1500,
      "items": [
        {
          "id": 18123,
          "amount": 3
        },
        {
          "id": 18106,
          "amount": 15
        },
        {
          "id": 18116,
          "amount": 12
        }
      ]
    }
  },
  "37400": {
    "from": 37440,
    "to": 37400,
    "cost": {
      "coins": 1500,
      "items": [
        {
          "id": 18125,
          "amount": 4
        },
        {
          "id": 18123,
          "amount": 2
        },
        {
          "id": 18116,
          "amount": 24
        }
      ]
    }
  },
  "37420": {
    "from": 37040,
    "to": 37420,
    "cost": {
      "coins": 450,
      "items": [
        {
          "id": 18105,
          "amount": 18
        },
        {
          "id": 18111,
          "amount": 12
        },
        {
          "id": 18115,
          "amount": 9
        }
      ]
    }
  },
  "37440": {
    "from": 37420,
    "to": 37440,
    "cost": {
      "coins": 500,
      "items": [
        {
          "id": 18105,
          "amount": 24
        },
        {
          "id": 18111,
          "amount": 18
        },
        {
          "id": 18115,
          "amount": 9
        }
      ]
    }
  },
  "37460": {
    "from": 37400,
    "to": 37460,
    "cost": {
      "coins": 2500,
      "items": [
        {
          "id": 18126,
          "amount": 6
        },
        {
          "id": 18123,
          "amount": 9
        },
        {
          "id": 18106,
          "amount": 21
        }
      ]
    }
  },
  "38060": {
    "from": 38040,
    "to": 38060,
    "cost": {
      "coins": 50,
      "items": [
        {
          "id": 18104,
          "amount": 12
        },
        {
          "id": 18107,
          "amount": 9
        },
        {
          "id": 18101,
          "amount": 9
        }
      ]
    }
  },
  "38140": {
    "from": 38060,
    "to": 38140,
    "cost": {
      "coins": 400,
      "items": [
        {
          "id": 18105,
          "amount": 18
        },
        {
          "id": 18108,
          "amount": 12
        },
        {
          "id": 18115,
          "amount": 9
        }
      ]
    }
  },
  "38160": {
    "from": 38140,
    "to": 38160,
    "cost": {
      "coins": 500,
      "items": [
        {
          "id": 18105,
          "amount": 24
        },
        {
          "id": 18108,
          "amount": 18
        },
        {
          "id": 18115,
          "amount": 9
        }
      ]
    }
  },
  "38240": {
    "from": 38160,
    "to": 38240,
    "cost": {
      "coins": 1500,
      "items": [
        {
          "id": 18123,
          "amount": 3
        },
        {
          "id": 18106,
          "amount": 15
        },
        {
          "id": 18116,
          "amount": 12
        }
      ]
    }
  },
  "38300": {
    "from": 38240,
    "to": 38300,
    "cost": {
      "coins": 2500,
      "items": [
        {
          "id": 18126,
          "amount": 6
        },
        {
          "id": 18123,
          "amount": 6
        },
        {
          "id": 18106,
          "amount": 24
        }
      ]
    }
  },
  "39040": {
    "from": 38040,
    "to": 39040,
    "cost": {
      "coins": 450,
      "items": [
        {
          "id": 18105,
          "amount": 18
        },
        {
          "id": 18108,
          "amount": 12
        },
        {
          "id": 18115,
          "amount": 9
        }
      ]
    }
  },
  "39060": {
    "from": 39040,
    "to": 39060,
    "cost": {
      "coins": 500,
      "items": [
        {
          "id": 18105,
          "amount": 24
        },
        {
          "id": 18108,
          "amount": 18
        },
        {
          "id": 18115,
          "amount": 9
        }
      ]
    }
  },
  "39140": {
    "from": 39060,
    "to": 39140,
    "cost": {
      "coins": 1500,
      "items": [
        {
          "id": 18123,
          "amount": 3
        },
        {
          "id": 18106,
          "amount": 15
        },
        {
          "id": 18116,
          "amount": 12
        }
      ]
    }
  },
  "39160": {
    "from": 39140,
    "to": 39160,
    "cost": {
      "coins": 2500,
      "items": [
        {
          "id": 18123,
          "amount": 9
        },
        {
          "id": 18106,
          "amount": 21
        },
        {
          "id": 18116,
          "amount": 18
        }
      ]
    }
  },
  "39240": {
    "from": 38040,
    "to": 39240,
    "cost": {
      "coins": 450,
      "items": [
        {
          "id": 18105,
          "amount": 18
        },
        {
          "id": 18108,
          "amount": 12
        },
        {
          "id": 18115,
          "amount": 9
        }
      ]
    }
  },
  "39300": {
    "from": 39240,
    "to": 39300,
    "cost": {
      "coins": 500,
      "items": [
        {
          "id": 18105,
          "amount": 24
        },
        {
          "id": 18108,
          "amount": 18
        },
        {
          "id": 18115,
          "amount": 9
        }
      ]
    }
  },
  "39320": {
    "from": 39140,
    "to": 39320,
    "cost": {
      "coins": 1500,
      "items": [
        {
          "id": 18114,
          "amount": 3
        },
        {
          "id": 18106,
          "amount": 6
        },
        {
          "id": 18116,
          "amount": 3
        }
      ]
    }
  },
  "39340": {
    "from": 39160,
    "to": 39340,
    "cost": {
      "coins": 10000,
      "items": [
        {
          "id": 18127,
          "amount": 6
        },
        {
          "id": 18123,
          "amount": 20
        },
        {
          "id": 18106,
          "amount": 60
        }
      ]
    }
  },
  "41060": {
    "from": 41040,
    "to": 41060,
    "cost": {
      "coins": 400,
      "items": [
        {
          "id": 18102,
          "amount": 18
        },
        {
          "id": 18111,
          "amount": 15
        },
        {
          "id": 18108,
          "amount": 15
        }
      ]
    }
  },
  "41140": {
    "from": 41060,
    "to": 41140,
    "cost": {
      "coins": 500,
      "items": [
        {
          "id": 18102,
          "amount": 24
        },
        {
          "id": 18111,
          "amount": 18
        },
        {
          "id": 18108,
          "amount": 18
        }
      ]
    }
  },
  "41160": {
    "from": 41140,
    "to": 41160,
    "cost": {
      "coins": 1500,
      "items": [
        {
          "id": 18117,
          "amount": 3
        },
        {
          "id": 18112,
          "amount": 15
        },
        {
          "id": 18109,
          "amount": 15
        }
      ]
    }
  },
  "42040": {
    "from": 42140,
    "to": 42040,
    "cost": {
      "coins": 400,
      "items": [
        {
          "id": 18102,
          "amount": 5
        },
        {
          "id": 18111,
          "amount": 5
        },
        {
          "id": 18108,
          "amount": 5
        }
      ]
    }
  },
  "42060": {
    "from": 42040,
    "to": 42060,
    "cost": {
      "coins": 500,
      "items": [
        {
          "id": 18102,
          "amount": 24
        },
        {
          "id": 18111,
          "amount": 18
        },
        {
          "id": 18108,
          "amount": 18
        }
      ]
    }
  },
  "42080": {
    "from": 42060,
    "to": 42080,
    "cost": {
      "coins": 4000,
      "items": [
        {
          "id": 18126,
          "amount": 7
        },
        {
          "id": 18117,
          "amount": 10
        },
        {
          "id": 18103,
          "amount": 48
        }
      ]
    }
  },
  "42160": {
    "from": 42140,
    "to": 42160,
    "cost": {
      "coins": 500,
      "items": [
        {
          "id": 18102,
          "amount": 24
        },
        {
          "id": 18111,
          "amount": 18
        },
        {
          "id": 18108,
          "amount": 18
        }
      ]
    }
  },
  "42240": {
    "from": 42340,
    "to": 42240,
    "cost": {
      "coins": 500,
      "items": [
        {
          "id": 18102,
          "amount": 24
        },
        {
          "id": 18111,
          "amount": 18
        },
        {
          "id": 18108,
          "amount": 18
        }
      ]
    }
  },
  "42340": {
    "from": 42040,
    "to": 42340,
    "cost": {
      "coins": 400,
      "items": [
        {
          "id": 18102,
          "amount": 5
        },
        {
          "id": 18111,
          "amount": 5
        },
        {
          "id": 18108,
          "amount": 5
        }
      ]
    }
  },
  "44140": {
    "from": 44040,
    "to": 44140,
    "cost": {
      "coins": 2000,
      "items": [
        {
          "id": 18117,
          "amount": 3
        },
        {
          "id": 18103,
          "amount": 21
        },
        {
          "id": 18106,
          "amount": 21
        }
      ]
    }
  },
  "44200": {
    "from": 44140,
    "to": 44200,
    "cost": {
      "coins": 2500,
      "items": [
        {
          "id": 18126,
          "amount": 6
        },
        {
          "id": 18117,
          "amount": 6
        },
        {
          "id": 18103,
          "amount": 24
        }
      ]
    }
  },
  "44300": {
    "from": 44040,
    "to": 44300,
    "cost": {
      "coins": 2000,
      "items": [
        {
          "id": 18126,
          "amount": 6
        },
        {
          "id": 18117,
          "amount": 2
        },
        {
          "id": 18106,
          "amount": 20
        }
      ]
    }
  },
  "44400": {
    "from": 44300,
    "to": 44400,
    "cost": {
      "coins": 2500,
      "items": [
        {
          "id": 18126,
          "amount": 6
        },
        {
          "id": 18117,
          "amount": 6
        },
        {
          "id": 18103,
          "amount": 24
        }
      ]
    }
  },
  "44500": {
    "from": 44300,
    "to": 44500,
    "cost": {
      "coins": 2500,
      "items": [
        {
          "id": 18126,
          "amount": 6
        },
        {
          "id": 18117,
          "amount": 6
        },
        {
          "id": 18106,
          "amount": 24
        }
      ]
    }
  },
  "45040": {
    "from": 5040,
    "to": 45040,
    "cost": {
      "coins": 450,
      "items": [
        {
          "id": 18108,
          "amount": 18
        },
        {
          "id": 18105,
          "amount": 12
        },
        {
          "id": 18113,
          "amount": 9
        }
      ]
    }
  },
  "45140": {
    "from": 5140,
    "to": 45140,
    "cost": {
      "coins": 2000,
      "items": [
        {
          "id": 18119,
          "amount": 3
        },
        {
          "id": 18109,
          "amount": 21
        },
        {
          "id": 18114,
          "amount": 18
        }
      ]
    }
  },
  "45141": {
    "from": 45040,
    "to": 45140,
    "cost": {
      "coins": 2000,
      "items": [
        {
          "id": 18119,
          "amount": 3
        },
        {
          "id": 18109,
          "amount": 21
        },
        {
          "id": 18114,
          "amount": 18
        }
      ]
    }
  },
  "45240": {
    "from": 5240,
    "to": 45240,
    "cost": {
      "coins": 10000,
      "items": [
        {
          "id": 18120,
          "amount": 9
        },
        {
          "id": 18109,
          "amount": 60
        },
        {
          "id": 18114,
          "amount": 48
        }
      ]
    }
  },
  "45241": {
    "from": 45140,
    "to": 45240,
    "cost": {
      "coins": 10000,
      "items": [
        {
          "id": 18120,
          "amount": 9
        },
        {
          "id": 18109,
          "amount": 60
        },
        {
          "id": 18114,
          "amount": 48
        }
      ]
    }
  },
  "45440": {
    "from": 45340,
    "to": 45440,
    "cost": {
      "coins": 2000,
      "items": [
        {
          "id": 18119,
          "amount": 3
        },
        {
          "id": 18109,
          "amount": 21
        },
        {
          "id": 18114,
          "amount": 18
        }
      ]
    }
  },
  "46040": {
    "from": 46140,
    "to": 46040,
    "cost": {
      "coins": 50,
      "items": [
        {
          "id": 18104,
          "amount": 12
        },
        {
          "id": 18101,
          "amount": 9
        },
        {
          "id": 18110,
          "amount": 9
        }
      ]
    }
  },
  "46060": {
    "from": 46040,
    "to": 46060,
    "cost": {
      "coins": 400,
      "items": [
        {
          "id": 18105,
          "amount": 18
        },
        {
          "id": 18102,
          "amount": 12
        },
        {
          "id": 18113,
          "amount": 9
        }
      ]
    }
  },
  "46240": {
    "from": 46040,
    "to": 46240,
    "cost": {
      "coins": 400,
      "items": [
        {
          "id": 18105,
          "amount": 18
        },
        {
          "id": 18102,
          "amount": 12
        },
        {
          "id": 18113,
          "amount": 9
        }
      ]
    }
  },
  "46260": {
    "from": 46240,
    "to": 46260,
    "cost": {
      "coins": 500,
      "items": [
        {
          "id": 18105,
          "amount": 24
        },
        {
          "id": 18102,
          "amount": 18
        },
        {
          "id": 18113,
          "amount": 9
        }
      ]
    }
  },
  "46340": {
    "from": 46060,
    "to": 46340,
    "cost": {
      "coins": 2000,
      "items": [
        {
          "id": 18121,
          "amount": 3
        },
        {
          "id": 18106,
          "amount": 21
        },
        {
          "id": 18114,
          "amount": 18
        }
      ]
    }
  },
  "46360": {
    "from": 46340,
    "to": 46360,
    "cost": {
      "coins": 2500,
      "items": [
        {
          "id": 18121,
          "amount": 9
        },
        {
          "id": 18106,
          "amount": 21
        },
        {
          "id": 18114,
          "amount": 18
        }
      ]
    }
  },
  "46380": {
    "from": 46360,
    "to": 46380,
    "cost": {
      "coins": 2500,
      "items": [
        {
          "id": 18112,
          "amount": 4
        },
        {
          "id": 18106,
          "amount": 8
        },
        {
          "id": 18114,
          "amount": 6
        }
      ]
    }
  },
  "46440": {
    "from": 46260,
    "to": 46440,
    "cost": {
      "coins": 400,
      "items": [
        {
          "id": 18105,
          "amount": 22
        },
        {
          "id": 18102,
          "amount": 5
        },
        {
          "id": 18113,
          "amount": 9
        }
      ]
    }
  },
  "47040": {
    "from": 47060,
    "to": 47040,
    "cost": {
      "coins": 450,
      "items": [
        {
          "id": 18105,
          "amount": 18
        },
        {
          "id": 18111,
          "amount": 12
        },
        {
          "id": 18115,
          "amount": 9
        }
      ]
    }
  },
  "47080": {
    "from": 47040,
    "to": 47080,
    "cost": {
      "coins": 500,
      "items": [
        {
          "id": 18125,
          "amount": 9
        },
        {
          "id": 18111,
          "amount": 18
        },
        {
          "id": 18115,
          "amount": 9
        }
      ]
    }
  },
  "47140": {
    "from": 47040,
    "to": 47140,
    "cost": {
      "coins": 2000,
      "items": [
        {
          "id": 18123,
          "amount": 3
        },
        {
          "id": 18106,
          "amount": 21
        },
        {
          "id": 18116,
          "amount": 18
        }
      ]
    }
  },
  "47160": {
    "from": 47040,
    "to": 47160,
    "cost": {
      "coins": 4500,
      "items": [
        {
          "id": 18126,
          "amount": 8
        },
        {
          "id": 18123,
          "amount": 10
        },
        {
          "id": 18116,
          "amount": 48
        }
      ]
    }
  },
  "47180": {
    "from": 47080,
    "to": 47180,
    "cost": {
      "coins": 1500,
      "items": [
        {
          "id": 18125,
          "amount": 4
        },
        {
          "id": 18123,
          "amount": 2
        },
        {
          "id": 18116,
          "amount": 24
        }
      ]
    }
  },
  "47200": {
    "from": 47080,
    "to": 47200,
    "cost": {
      "coins": 1500,
      "items": [
        {
          "id": 18125,
          "amount": 4
        },
        {
          "id": 18123,
          "amount": 2
        },
        {
          "id": 18116,
          "amount": 24
        }
      ]
    }
  },
  "48000": {
    "from": 49060,
    "to": 48000,
    "cost": {
      "coins": 50,
      "items": [
        {
          "id": 18104,
          "amount": 12
        },
        {
          "id": 18107,
          "amount": 9
        },
        {
          "id": 18101,
          "amount": 9
        }
      ]
    }
  },
  "48020": {
    "from": 48000,
    "to": 48020,
    "cost": {
      "coins": 400,
      "items": [
        {
          "id": 18105,
          "amount": 18
        },
        {
          "id": 18108,
          "amount": 12
        },
        {
          "id": 18115,
          "amount": 9
        }
      ]
    }
  },
  "48040": {
    "from": 48020,
    "to": 48040,
    "cost": {
      "coins": 2000,
      "items": [
        {
          "id": 18123,
          "amount": 3
        },
        {
          "id": 18106,
          "amount": 21
        },
        {
          "id": 18116,
          "amount": 18
        }
      ]
    }
  },
  "49040": {
    "from": 49060,
    "to": 49040,
    "cost": {
      "coins": 450,
      "items": [
        {
          "id": 18105,
          "amount": 18
        },
        {
          "id": 18108,
          "amount": 12
        },
        {
          "id": 18115,
          "amount": 9
        }
      ]
    }
  },
  "90140": {
    "from": 90740,
    "to": 90140,
    "cost": {
      "coins": 2000,
      "items": [
        {
          "id": 18117,
          "amount": 3
        },
        {
          "id": 18112,
          "amount": 21
        },
        {
          "id": 18109,
          "amount": 21
        }
      ]
    }
  },
  "90240": {
    "from": 90800,
    "to": 90240,
    "cost": {
      "coins": 50,
      "items": [
        {
          "id": 18101,
          "amount": 12
        },
        {
          "id": 18110,
          "amount": 9
        },
        {
          "id": 18107,
          "amount": 9
        }
      ]
    }
  },
  "90340": {
    "from": 90460,
    "to": 90340,
    "cost": {
      "coins": 450,
      "items": [
        {
          "id": 18102,
          "amount": 18
        },
        {
          "id": 18111,
          "amount": 15
        },
        {
          "id": 18108,
          "amount": 15
        }
      ]
    }
  },
  "90440": {
    "from": 90340,
    "to": 90440,
    "cost": {
      "coins": 2000,
      "items": [
        {
          "id": 18117,
          "amount": 3
        },
        {
          "id": 18103,
          "amount": 21
        },
        {
          "id": 18106,
          "amount": 21
        }
      ]
    }
  },
  "90540": {
    "from": 90040,
    "to": 90540,
    "cost": {
      "coins": 450,
      "items": [
        {
          "id": 18102,
          "amount": 18
        },
        {
          "id": 18111,
          "amount": 15
        },
        {
          "id": 18108,
          "amount": 15
        }
      ]
    }
  },
  "90580": {
    "from": 90560,
    "to": 90580,
    "cost": {
      "coins": 450,
      "items": [
        {
          "id": 18105,
          "amount": 18
        },
        {
          "id": 18102,
          "amount": 12
        },
        {
          "id": 18113,
          "amount": 9
        }
      ]
    }
  },
  "90600": {
    "from": 90580,
    "to": 90600,
    "cost": {
      "coins": 2000,
      "items": [
        {
          "id": 18121,
          "amount": 3
        },
        {
          "id": 18106,
          "amount": 21
        },
        {
          "id": 18114,
          "amount": 18
        }
      ]
    }
  },
  "90620": {
    "from": 90600,
    "to": 90620,
    "cost": {
      "coins": 10000,
      "items": [
        {
          "id": 18122,
          "amount": 9
        },
        {
          "id": 18106,
          "amount": 60
        },
        {
          "id": 18114,
          "amount": 48
        }
      ]
    }
  },
  "90740": {
    "from": 90760,
    "to": 90740,
    "cost": {
      "coins": 450,
      "items": [
        {
          "id": 18102,
          "amount": 18
        },
        {
          "id": 18111,
          "amount": 15
        },
        {
          "id": 18108,
          "amount": 15
        }
      ]
    }
  },
  "90780": {
    "from": 90800,
    "to": 90780,
    "cost": {
      "coins": 50,
      "items": [
        {
          "id": 18101,
          "amount": 12
        },
        {
          "id": 18110,
          "amount": 9
        },
        {
          "id": 18107,
          "amount": 9
        }
      ]
    }
  },
  "90900": {
    "from": 91140,
    "to": 90900,
    "cost": {
      "coins": 2000,
      "items": [
        {
          "id": 18117,
          "amount": 3
        },
        {
          "id": 18103,
          "amount": 21
        },
        {
          "id": 18109,
          "amount": 21
        }
      ]
    }
  },
  "91000": {
    "from": 90440,
    "to": 91000,
    "cost": {
      "coins": 2500,
      "items": [
        {
          "id": 18126,
          "amount": 6
        },
        {
          "id": 18117,
          "amount": 6
        },
        {
          "id": 18103,
          "amount": 24
        }
      ]
    }
  },
  "91140": {
    "from": 7340,
    "to": 91140,
    "cost": {
      "coins": 400,
      "items": [
        {
          "id": 18102,
          "amount": 18
        },
        {
          "id": 18111,
          "amount": 15
        },
        {
          "id": 18108,
          "amount": 15
        }
      ]
    }
  },
  "91220": {
    "from": 91380,
    "to": 91220,
    "cost": {
      "coins": 900,
      "items": [
        {
          "id": 18105,
          "amount": 30
        },
        {
          "id": 18111,
          "amount": 30
        },
        {
          "id": 18115,
          "amount": 24
        }
      ]
    }
  },
  "91240": {
    "from": 91360,
    "to": 91240,
    "cost": {
      "coins": 4000,
      "items": [
        {
          "id": 18123,
          "amount": 9
        },
        {
          "id": 18106,
          "amount": 30
        },
        {
          "id": 18116,
          "amount": 30
        }
      ]
    }
  },
  "91300": {
    "from": 90840,
    "to": 91300,
    "cost": {
      "coins": 50,
      "items": [
        {
          "id": 18104,
          "amount": 12
        },
        {
          "id": 18107,
          "amount": 9
        },
        {
          "id": 18101,
          "amount": 9
        }
      ]
    }
  },
  "91320": {
    "from": 91300,
    "to": 91320,
    "cost": {
      "coins": 400,
      "items": [
        {
          "id": 18105,
          "amount": 18
        },
        {
          "id": 18108,
          "amount": 12
        },
        {
          "id": 18115,
          "amount": 9
        }
      ]
    }
  },
  "91340": {
    "from": 91320,
    "to": 91340,
    "cost": {
      "coins": 2000,
      "items": [
        {
          "id": 18123,
          "amount": 3
        },
        {
          "id": 18106,
          "amount": 21
        },
        {
          "id": 18116,
          "amount": 18
        }
      ]
    }
  },
  "91360": {
    "from": 91300,
    "to": 91360,
    "cost": {
      "coins": 900,
      "items": [
        {
          "id": 18108,
          "amount": 30
        },
        {
          "id": 18105,
          "amount": 30
        },
        {
          "id": 18115,
          "amount": 30
        }
      ]
    }
  },
  "91380": {
    "from": 90820,
    "to": 91380,
    "cost": {
      "coins": 50,
      "items": [
        {
          "id": 18104,
          "amount": 12
        },
        {
          "id": 18110,
          "amount": 9
        },
        {
          "id": 18101,
          "amount": 9
        }
      ]
    }
  },
  "95040": {
    "from": 96160,
    "to": 95040,
    "cost": {
      "coins": 2400,
      "items": [
        {
          "id": 18117,
          "amount": 3
        },
        {
          "id": 18103,
          "amount": 24
        },
        {
          "id": 18106,
          "amount": 30
        }
      ]
    }
  },
  "95140": {
    "from": 96200,
    "to": 95140,
    "cost": {
      "coins": 1500,
      "items": [
        {
          "id": 18121,
          "amount": 3
        },
        {
          "id": 18106,
          "amount": 15
        },
        {
          "id": 18114,
          "amount": 12
        }
      ]
    }
  },
  "95160": {
    "from": 95140,
    "to": 95160,
    "cost": {
      "coins": 2500,
      "items": [
        {
          "id": 18126,
          "amount": 6
        },
        {
          "id": 18121,
          "amount": 6
        },
        {
          "id": 18106,
          "amount": 24
        }
      ]
    }
  },
  "95440": {
    "from": 95580,
    "to": 95440,
    "cost": {
      "coins": 500,
      "items": [
        {
          "id": 18102,
          "amount": 24
        },
        {
          "id": 18111,
          "amount": 18
        },
        {
          "id": 18108,
          "amount": 18
        }
      ]
    }
  },
  "95480": {
    "from": 96140,
    "to": 95480,
    "cost": {
      "coins": 50,
      "items": [
        {
          "id": 18101,
          "amount": 12
        },
        {
          "id": 18110,
          "amount": 9
        },
        {
          "id": 18104,
          "amount": 9
        }
      ]
    }
  },
  "95540": {
    "from": 96180,
    "to": 95540,
    "cost": {
      "coins": 450,
      "items": [
        {
          "id": 18105,
          "amount": 18
        },
        {
          "id": 18102,
          "amount": 12
        },
        {
          "id": 18113,
          "amount": 9
        }
      ]
    }
  },
  "95580": {
    "from": 95460,
    "to": 95580,
    "cost": {
      "coins": 450,
      "items": [
        {
          "id": 18102,
          "amount": 18
        },
        {
          "id": 18111,
          "amount": 15
        },
        {
          "id": 18108,
          "amount": 15
        }
      ]
    }
  },
  "95900": {
    "from": 95040,
    "to": 95900,
    "cost": {
      "coins": 2500,
      "items": [
        {
          "id": 18126,
          "amount": 6
        },
        {
          "id": 18117,
          "amount": 6
        },
        {
          "id": 18103,
          "amount": 24
        }
      ]
    }
  },
  "95960": {
    "from": 95440,
    "to": 95960,
    "cost": {
      "coins": 4000,
      "items": [
        {
          "id": 18117,
          "amount": 9
        },
        {
          "id": 18103,
          "amount": 24
        },
        {
          "id": 18109,
          "amount": 54
        }
      ]
    }
  },
  "96160": {
    "from": 96140,
    "to": 96160,
    "cost": {
      "coins": 50,
      "items": [
        {
          "id": 18101,
          "amount": 12
        },
        {
          "id": 18110,
          "amount": 9
        },
        {
          "id": 18104,
          "amount": 9
        }
      ]
    }
  },
  "96200": {
    "from": 95540,
    "to": 96200,
    "cost": {
      "coins": 500,
      "items": [
        {
          "id": 18105,
          "amount": 24
        },
        {
          "id": 18102,
          "amount": 18
        },
        {
          "id": 18113,
          "amount": 9
        }
      ]
    }
  },
  "96220": {
    "from": 96180,
    "to": 96220,
    "cost": {
      "coins": 450,
      "items": [
        {
          "id": 18105,
          "amount": 18
        },
        {
          "id": 18102,
          "amount": 12
        },
        {
          "id": 18113,
          "amount": 9
        }
      ]
    }
  }
}